[
    {
      "datas": {
        "year": 2017,
        "month": 2,
        "dayOfMonth": 1,
        "hourOfDay": 0,
        "minute": 0,
        "second": 0
      },
      "textoIdentificador": "Saldo Corrente",
      "valor": 89731.57,
      "descricao": "Saldo inicial do mes",
      "numeroDOC": "00000000",
      "classificada": true,
      "tipos": [
        "OUTRAS_RECEITAS",
        "SALDO_CORRENTE"
      ],
      "arquivos": []
    },
    {
      "datas": {
        "year": 2017,
        "month": 2,
        "dayOfMonth": 1,
        "hourOfDay": 8,
        "minute": 15,
        "second": 22
      },
      "textoIdentificador": "CHQ CMP INTEGRADA",
      "valor": -10271.16,
      "descricao": "",
      "numeroDOC": "002.126",
      "classificada": false,
      "tipos": [
        "OUTROS"
      ],
      "arquivos": []
    },
    {
        "datas": {
          "year": 2017,
          "month": 2,
          "dayOfMonth": 1,
          "hourOfDay": 8,
          "minute": 15,
          "second": 22
        },
        "textoIdentificador": "CHQ CMP INTEGRADA",
        "valor": -80.0,
        "descricao": "",
        "numeroDOC": "002.216",
        "classificada": false,
        "tipos": [
          "OUTROS"
        ],
        "arquivos": []
      },
      {
        "datas": {
          "year": 2018,
          "month": 2,
          "dayOfMonth": 1,
          "hourOfDay": 8,
          "minute": 15,
          "second": 22
        },
        "textoIdentificador": "CRÉD.LIQ.COBRANÇA",
        "valor": 1152.11,
        "descricao": "",
        "numeroDOC": "0023522701",
        "classificada": false,
        "tipos": [
          "OUTRAS_RECEITAS"
        ],
        "arquivos": []
      },
      {
        "datas": {
          "year": 2018,
          "month": 2,
          "dayOfMonth": 1,
          "hourOfDay": 8,
          "minute": 15,
          "second": 22
        },
        "textoIdentificador": "DEB.PARC.SUBS/INTEG",
        "valor": -50.0,
        "descricao": "",
        "numeroDOC": "1085",
        "classificada": false,
        "tipos": [
          "OUTROS"
        ],
        "arquivos": []
      },
      {
        "datas": {
          "year": 2016,
          "month": 2,
          "dayOfMonth": 1,
          "hourOfDay": 8,
          "minute": 15,
          "second": 22
        },
        "textoIdentificador": "TARIFA COBRANÇA",
        "valor": -17.4,
        "descricao": "",
        "numeroDOC": "0023522701",
        "classificada": true,
        "tipos": [
          "DESPESAS_ADMINISTRATIVAS",
          "TARIFAS_BANCARIAS"
        ],
        "arquivos": []
      },
      {
        "datas": {
          "year": 2016,
          "month": 2,
          "dayOfMonth": 1,
          "hourOfDay": 8,
          "minute": 15,
          "second": 22
        },
        "textoIdentificador": "CRÉD.LIQ.COBRANÇA",
        "valor": 1152.11,
        "descricao": "",
        "numeroDOC": "ICP-4291",
        "classificada": false,
        "tipos": [
          "OUTRAS_RECEITAS"
        ],
        "arquivos": []
      },
      {
        "datas": {
          "year": 2016,
          "month": 2,
          "dayOfMonth": 1,
          "hourOfDay": 8,
          "minute": 15,
          "second": 22
        },
        "textoIdentificador": "TARIFA COBRANÇA",
        "valor": -17.4,
        "descricao": "",
        "numeroDOC": "ICP-4291",
        "classificada": true,
        "tipos": [
          "DESPESAS_ADMINISTRATIVAS",
          "TARIFAS_BANCARIAS"
        ],
        "arquivos": []
      },
      {
        "datas": {
          "year": 2016,
          "month": 2,
          "dayOfMonth": 1,
          "hourOfDay": 8,
          "minute": 15,
          "second": 22
        },
        "textoIdentificador": "TARIFA PRÉ-DEPÓSITO",
        "valor": -10.27,
        "descricao": "",
        "numeroDOC": "67",
        "classificada": true,
        "tipos": [
          "DESPESAS_ADMINISTRATIVAS",
          "TARIFAS_BANCARIAS"
        ],
        "arquivos": []
      }
]